allink_essentials/__init__.py
allink_essentials/analytics/__init__.py
allink_essentials/analytics/ecommerce.py
allink_essentials/analytics/templates/analytics/google-analytics.html
allink_essentials/analytics/templates/analytics/google-ecommerce.html
allink_essentials/analytics/templates/analytics/google-tag-manager.html
allink_essentials/analytics/templatetags/__init__.py
allink_essentials/analytics/templatetags/analytics_tags.py
allink_essentials/fabfiles/__init__.py
allink_essentials/fabfiles/nexa3_class_fabfile.py
allink_essentials/fabfiles/nexa_class_fabfile.py
allink_essentials/fabfiles/nexa_class_fabfile_legacy_django13.py
allink_essentials/fabfiles/pestalozzi_class_fabfile.py
allink_essentials/fabfiles/proxima_class_fabfile.py
allink_essentials/feincms_extensions/__init__.py
allink_essentials/feincms_extensions/metas.py
allink_essentials/feincms_extensions/metas_v2.py
allink_essentials/feincms_extensions/socials.py
allink_essentials/in_footer/__init__.py
allink_essentials/in_footer/models.py
allink_essentials/in_footer/page_extension.py
allink_essentials/in_footer/page_extension_v2.py
allink_essentials/in_footer/templatetags/__init__.py
allink_essentials/in_footer/templatetags/in_footer.py
allink_essentials/legacy_redirect/__init__.py
allink_essentials/legacy_redirect/admin.py
allink_essentials/legacy_redirect/apps.py
allink_essentials/legacy_redirect/forms.py
allink_essentials/legacy_redirect/middleware.py
allink_essentials/legacy_redirect/models.py
allink_essentials/legacy_redirect/resources.py
allink_essentials/legacy_redirect/utils.py
allink_essentials/legacy_redirect/migrations/0001_initial.py
allink_essentials/legacy_redirect/migrations/0002_legacylink_active.py
allink_essentials/legacy_redirect/migrations/0003_auto_20160224_1216.py
allink_essentials/legacy_redirect/migrations/0004_legacylink_match_subpages.py
allink_essentials/legacy_redirect/migrations/0005_legacylink_overwrite.py
allink_essentials-1.1.12.dist-info/DESCRIPTION.rst
allink_essentials-1.1.12.dist-info/METADATA
allink_essentials-1.1.12.dist-info/RECORD
allink_essentials-1.1.12.dist-info/WHEEL
allink_essentials-1.1.12.dist-info/metadata.json
allink_essentials-1.1.12.dist-info/top_level.txt
