Metadata-Version: 2.0
Name: allink-essentials
Version: 1.1.12
Summary: collection of code fragments
Home-page: http://github.com/allink/allink-essentials/
Author: Leandra Finger, Marc Egli
Author-email: itcrowd@allink.ch
License: BSD License
Platform: OS Independent
Classifier: Development Status :: 3 - Alpha
Classifier: Environment :: Web Environment
Classifier: Framework :: Django
Classifier: Intended Audience :: Developers
Classifier: License :: OSI Approved :: BSD License
Classifier: Operating System :: OS Independent
Classifier: Programming Language :: Python :: 2.7
Classifier: Topic :: Internet :: WWW/HTTP :: Dynamic Content
Classifier: Topic :: Communications :: Email
